{
    "name": "scene",
    "objects": [
        {
            "type": "MESH",
            "name": "Ground",
            "transform": {
                "translation": [
                    -195.29006958007812,
                    290.4986572265625,
                    -2.9999961853027344
                ],
                "rotation": [
                    0.0,
                    -0.0,
                    0.0
                ],
                "scaling": [
                    1000.0,
                    1000.0,
                    1.0
                ]
            },
            "file_name": "cube.gltf",
            "collider": {
                "type": "BOX",
                "center": [
                    0.0,
                    0.0,
                    0.0
                ],
                "size": [
                    1.0,
                    1.0,
                    1.0
                ]
            }
        },
        {
            "type": "CAMERA",
            "name": "Camera",
            "transform": {
                "translation": [
                    -187.93118286132812,
                    283.5728759765625,
                    4.95831298828125
                ],
                "rotation": [
                    63.559295654296875,
                    2.2983238068263745e-07,
                    46.69194412231445
                ],
                "scaling": [
                    1.0,
                    1.0,
                    1.0
                ]
            }
        },
        {
            "type": "MESH",
            "name": "pillar.northwest",
            "transform": {
                "translation": [
                    -582.5735473632812,
                    686.7605590820312,
                    140.0
                ],
                "rotation": [
                    0.0,
                    -0.0,
                    0.0
                ],
                "scaling": [
                    50.0,
                    50.0,
                    150.0
                ]
            },
            "file_name": "cube.gltf",
            "collider": {
                "type": "BOX",
                "center": [
                    0.0,
                    0.0,
                    0.0
                ],
                "size": [
                    1.0,
                    1.0,
                    1.0
                ]
            }
        },
        {
            "type": "MESH",
            "name": "pillar.west",
            "transform": {
                "translation": [
                    -589.4812622070312,
                    98.96136474609375,
                    140.0
                ],
                "rotation": [
                    0.0,
                    -0.0,
                    0.0
                ],
                "scaling": [
                    50.000003814697266,
                    50.000003814697266,
                    150.0
                ]
            },
            "file_name": "cube.gltf",
            "collider": {
                "type": "BOX",
                "center": [
                    0.0,
                    0.0,
                    0.0
                ],
                "size": [
                    1.0,
                    1.0,
                    1.0
                ]
            }
        },
        {
            "type": "MESH",
            "name": "pillar.Southwest",
            "transform": {
                "translation": [
                    -589.4812622070312,
                    -487.1339111328125,
                    140.0
                ],
                "rotation": [
                    0.0,
                    -0.0,
                    0.0
                ],
                "scaling": [
                    50.000003814697266,
                    50.000003814697266,
                    150.0
                ]
            },
            "file_name": "cube.gltf",
            "collider": {
                "type": "BOX",
                "center": [
                    0.0,
                    0.0,
                    0.0
                ],
                "size": [
                    1.0,
                    1.0,
                    1.0
                ]
            }
        },
        {
            "type": "MESH",
            "name": "pillar.South",
            "transform": {
                "translation": [
                    -2.7387046813964844,
                    -505.4844970703125,
                    140.0
                ],
                "rotation": [
                    0.0,
                    -0.0,
                    0.0
                ],
                "scaling": [
                    50.0,
                    50.0,
                    150.0
                ]
            },
            "file_name": "cube.gltf",
            "collider": {
                "type": "BOX",
                "center": [
                    0.0,
                    0.0,
                    0.0
                ],
                "size": [
                    1.0,
                    1.0,
                    1.0
                ]
            }
        },
        {
            "type": "MESH",
            "name": "pillar.SouthEast",
            "transform": {
                "translation": [
                    571.2139892578125,
                    -505.4844970703125,
                    140.0
                ],
                "rotation": [
                    0.0,
                    -0.0,
                    0.0
                ],
                "scaling": [
                    50.0,
                    50.0,
                    150.0
                ]
            },
            "file_name": "cube.gltf",
            "collider": {
                "type": "BOX",
                "center": [
                    0.0,
                    0.0,
                    0.0
                ],
                "size": [
                    1.0,
                    1.0,
                    1.0
                ]
            }
        },
        {
            "type": "MESH",
            "name": "Cube.102",
            "transform": {
                "translation": [
                    293.79278564453125,
                    -513.9575805664062,
                    73.5116958618164
                ],
                "rotation": [
                    0.0,
                    -0.0,
                    0.0
                ],
                "scaling": [
                    250.00001525878906,
                    30.000001907348633,
                    93.0447006225586
                ]
            },
            "file_name": "cube.gltf",
            "collider": {
                "type": "BOX",
                "center": [
                    0.0,
                    0.0,
                    0.0
                ],
                "size": [
                    1.0,
                    1.0,
                    1.0
                ]
            }
        },
        {
            "type": "MESH",
            "name": "pillar.East",
            "transform": {
                "translation": [
                    598.4993896484375,
                    72.2244873046875,
                    140.0
                ],
                "rotation": [
                    0.0,
                    -0.0,
                    0.0
                ],
                "scaling": [
                    49.999996185302734,
                    49.999996185302734,
                    150.0
                ]
            },
            "file_name": "cube.gltf",
            "collider": {
                "type": "BOX",
                "center": [
                    0.0,
                    0.0,
                    0.0
                ],
                "size": [
                    1.0,
                    1.0,
                    1.0
                ]
            }
        },
        {
            "type": "MESH",
            "name": "Cube.140",
            "transform": {
                "translation": [
                    581.9552001953125,
                    -167.17300415039062,
                    33.63540267944336
                ],
                "rotation": [
                    0.0,
                    -0.0,
                    0.0
                ],
                "scaling": [
                    10.000000953674316,
                    10.000000953674316,
                    42.53472137451172
                ]
            },
            "file_name": "cube.gltf",
            "collider": {
                "type": "BOX",
                "center": [
                    0.0,
                    0.0,
                    0.0
                ],
                "size": [
                    1.0,
                    1.0,
                    1.0
                ]
            }
        },
        {
            "type": "MESH",
            "name": "Cube.141",
            "transform": {
                "translation": [
                    601.876708984375,
                    -235.4122314453125,
                    73.5116958618164
                ],
                "rotation": [
                    0.0,
                    -0.0,
                    0.0
                ],
                "scaling": [
                    10.000000953674316,
                    10.000000953674316,
                    93.0447006225586
                ]
            },
            "file_name": "cube.gltf",
            "collider": {
                "type": "BOX",
                "center": [
                    0.0,
                    0.0,
                    0.0
                ],
                "size": [
                    1.0,
                    1.0,
                    1.0
                ]
            }
        },
        {
            "type": "MESH",
            "name": "Cube.142",
            "transform": {
                "translation": [
                    600.5145263671875,
                    -256.5362548828125,
                    62.0345573425293
                ],
                "rotation": [
                    0.0,
                    -0.0,
                    0.0
                ],
                "scaling": [
                    10.000000953674316,
                    10.000000953674316,
                    95.55487823486328
                ]
            },
            "file_name": "cube.gltf",
            "collider": {
                "type": "BOX",
                "center": [
                    0.0,
                    0.0,
                    0.0
                ],
                "size": [
                    1.0,
                    1.0,
                    1.0
                ]
            }
        },
        {
            "type": "MESH",
            "name": "Cube.143",
            "transform": {
                "translation": [
                    581.0758666992188,
                    -204.62246704101562,
                    70.0
                ],
                "rotation": [
                    0.0,
                    -0.0,
                    0.0
                ],
                "scaling": [
                    30.0,
                    10.000000953674316,
                    80.0
                ]
            },
            "file_name": "cube.gltf",
            "collider": {
                "type": "BOX",
                "center": [
                    0.0,
                    0.0,
                    0.0
                ],
                "size": [
                    1.0,
                    1.0,
                    1.0
                ]
            }
        },
        {
            "type": "MESH",
            "name": "Cube.144",
            "transform": {
                "translation": [
                    576.288330078125,
                    -408.498291015625,
                    73.0
                ],
                "rotation": [
                    0.0,
                    -0.0,
                    0.0
                ],
                "scaling": [
                    20.0,
                    20.0,
                    93.0
                ]
            },
            "file_name": "cube.gltf",
            "collider": {
                "type": "BOX",
                "center": [
                    0.0,
                    0.0,
                    0.0
                ],
                "size": [
                    1.0,
                    1.0,
                    1.0
                ]
            }
        },
        {
            "type": "MESH",
            "name": "Cube.145",
            "transform": {
                "translation": [
                    573.4253540039062,
                    -352.30462646484375,
                    59.40877914428711
                ],
                "rotation": [
                    0.0,
                    -0.0,
                    0.0
                ],
                "scaling": [
                    10.000000953674316,
                    10.000000953674316,
                    66.08507537841797
                ]
            },
            "file_name": "cube.gltf",
            "collider": {
                "type": "BOX",
                "center": [
                    0.0,
                    0.0,
                    0.0
                ],
                "size": [
                    1.0,
                    1.0,
                    1.0
                ]
            }
        },
        {
            "type": "MESH",
            "name": "Cube.146",
            "transform": {
                "translation": [
                    577.167724609375,
                    -371.048828125,
                    95.0
                ],
                "rotation": [
                    0.0,
                    -0.0,
                    0.0
                ],
                "scaling": [
                    30.799997329711914,
                    10.000000953674316,
                    100.52471923828125
                ]
            },
            "file_name": "cube.gltf",
            "collider": {
                "type": "BOX",
                "center": [
                    0.0,
                    0.0,
                    0.0
                ],
                "size": [
                    1.0,
                    1.0,
                    1.0
                ]
            }
        },
        {
            "type": "MESH",
            "name": "Cube.148",
            "transform": {
                "translation": [
                    592.080078125,
                    -340.786376953125,
                    73.5116958618164
                ],
                "rotation": [
                    0.0,
                    -0.0,
                    0.0
                ],
                "scaling": [
                    10.000000953674316,
                    10.000000953674316,
                    93.0447006225586
                ]
            },
            "file_name": "cube.gltf",
            "collider": {
                "type": "BOX",
                "center": [
                    0.0,
                    0.0,
                    0.0
                ],
                "size": [
                    1.0,
                    1.0,
                    1.0
                ]
            }
        },
        {
            "type": "MESH",
            "name": "Cube.149",
            "transform": {
                "translation": [
                    599.007568359375,
                    -320.70672607421875,
                    62.0345573425293
                ],
                "rotation": [
                    0.0,
                    -0.0,
                    0.0
                ],
                "scaling": [
                    10.000000953674316,
                    10.000000953674316,
                    84.79031372070312
                ]
            },
            "file_name": "cube.gltf",
            "collider": {
                "type": "BOX",
                "center": [
                    0.0,
                    0.0,
                    0.0
                ],
                "size": [
                    1.0,
                    1.0,
                    1.0
                ]
            }
        },
        {
            "type": "MESH",
            "name": "Cube.150",
            "transform": {
                "translation": [
                    591.1782836914062,
                    -288.27801513671875,
                    100.0
                ],
                "rotation": [
                    0.0,
                    -0.0,
                    0.0
                ],
                "scaling": [
                    24.999998092651367,
                    24.999998092651367,
                    110.0
                ]
            },
            "file_name": "cube.gltf",
            "collider": {
                "type": "BOX",
                "center": [
                    0.0,
                    0.0,
                    0.0
                ],
                "size": [
                    1.0,
                    1.0,
                    1.0
                ]
            }
        },
        {
            "type": "MESH",
            "name": "Cube.156",
            "transform": {
                "translation": [
                    597.08935546875,
                    -439.28790283203125,
                    73.0
                ],
                "rotation": [
                    0.0,
                    -0.0,
                    0.0
                ],
                "scaling": [
                    30.0,
                    10.000000953674316,
                    93.0447006225586
                ]
            },
            "file_name": "cube.gltf",
            "collider": {
                "type": "BOX",
                "center": [
                    0.0,
                    0.0,
                    0.0
                ],
                "size": [
                    1.0,
                    1.0,
                    1.0
                ]
            }
        },
        {
            "type": "MESH",
            "name": "pillar.northEast",
            "transform": {
                "translation": [
                    598.4993896484375,
                    660.1439208984375,
                    140.0
                ],
                "rotation": [
                    0.0,
                    -0.0,
                    0.0
                ],
                "scaling": [
                    49.999996185302734,
                    49.999996185302734,
                    150.0
                ]
            },
            "file_name": "cube.gltf",
            "collider": {
                "type": "BOX",
                "center": [
                    0.0,
                    0.0,
                    0.0
                ],
                "size": [
                    1.0,
                    1.0,
                    1.0
                ]
            }
        },
        {
            "type": "MESH",
            "name": "Cube.168",
            "transform": {
                "translation": [
                    580.6139526367188,
                    541.7464599609375,
                    59.40877914428711
                ],
                "rotation": [
                    0.0,
                    -0.0,
                    0.0
                ],
                "scaling": [
                    10.000000953674316,
                    10.000000953674316,
                    66.08507537841797
                ]
            },
            "file_name": "cube.gltf",
            "collider": {
                "type": "BOX",
                "center": [
                    0.0,
                    0.0,
                    0.0
                ],
                "size": [
                    1.0,
                    1.0,
                    1.0
                ]
            }
        },
        {
            "type": "MESH",
            "name": "Cube.169",
            "transform": {
                "translation": [
                    584.3496704101562,
                    518.98876953125,
                    73.0
                ],
                "rotation": [
                    0.0,
                    -0.0,
                    0.0
                ],
                "scaling": [
                    20.0,
                    10.000000953674316,
                    80.85472106933594
                ]
            },
            "file_name": "cube.gltf",
            "collider": {
                "type": "BOX",
                "center": [
                    0.0,
                    0.0,
                    0.0
                ],
                "size": [
                    1.0,
                    1.0,
                    1.0
                ]
            }
        },
        {
            "type": "MESH",
            "name": "Cube.170",
            "transform": {
                "translation": [
                    607.5548095703125,
                    592.2774658203125,
                    73.5116958618164
                ],
                "rotation": [
                    0.0,
                    -0.0,
                    0.0
                ],
                "scaling": [
                    30.0,
                    30.0,
                    93.0447006225586
                ]
            },
            "file_name": "cube.gltf",
            "collider": {
                "type": "BOX",
                "center": [
                    0.0,
                    0.0,
                    0.0
                ],
                "size": [
                    1.0,
                    1.0,
                    1.0
                ]
            }
        },
        {
            "type": "MESH",
            "name": "Cube.172",
            "transform": {
                "translation": [
                    596.867431640625,
                    451.0087585449219,
                    73.5116958618164
                ],
                "rotation": [
                    0.0,
                    -0.0,
                    0.0
                ],
                "scaling": [
                    20.0,
                    10.000000953674316,
                    93.0447006225586
                ]
            },
            "file_name": "cube.gltf",
            "collider": {
                "type": "BOX",
                "center": [
                    0.0,
                    0.0,
                    0.0
                ],
                "size": [
                    1.0,
                    1.0,
                    1.0
                ]
            }
        },
        {
            "type": "MESH",
            "name": "Cube.173",
            "transform": {
                "translation": [
                    605.1572265625,
                    492.2125549316406,
                    73.5116958618164
                ],
                "rotation": [
                    0.0,
                    -0.0,
                    0.0
                ],
                "scaling": [
                    10.000000953674316,
                    10.000000953674316,
                    93.0447006225586
                ]
            },
            "file_name": "cube.gltf",
            "collider": {
                "type": "BOX",
                "center": [
                    0.0,
                    0.0,
                    0.0
                ],
                "size": [
                    1.0,
                    1.0,
                    1.0
                ]
            }
        },
        {
            "type": "MESH",
            "name": "Cube.175",
            "transform": {
                "translation": [
                    601.876708984375,
                    352.5072021484375,
                    73.5116958618164
                ],
                "rotation": [
                    0.0,
                    -0.0,
                    0.0
                ],
                "scaling": [
                    10.000000953674316,
                    10.000000953674316,
                    93.0447006225586
                ]
            },
            "file_name": "cube.gltf",
            "collider": {
                "type": "BOX",
                "center": [
                    0.0,
                    0.0,
                    0.0
                ],
                "size": [
                    1.0,
                    1.0,
                    1.0
                ]
            }
        },
        {
            "type": "MESH",
            "name": "Cube.176",
            "transform": {
                "translation": [
                    600.5145263671875,
                    331.3831787109375,
                    62.0345573425293
                ],
                "rotation": [
                    0.0,
                    -0.0,
                    0.0
                ],
                "scaling": [
                    10.000000953674316,
                    10.000000953674316,
                    95.55487823486328
                ]
            },
            "file_name": "cube.gltf",
            "collider": {
                "type": "BOX",
                "center": [
                    0.0,
                    0.0,
                    0.0
                ],
                "size": [
                    1.0,
                    1.0,
                    1.0
                ]
            }
        },
        {
            "type": "MESH",
            "name": "Cube.178",
            "transform": {
                "translation": [
                    576.288330078125,
                    179.421142578125,
                    73.0
                ],
                "rotation": [
                    0.0,
                    -0.0,
                    0.0
                ],
                "scaling": [
                    20.0,
                    20.0,
                    93.0
                ]
            },
            "file_name": "cube.gltf",
            "collider": {
                "type": "BOX",
                "center": [
                    0.0,
                    0.0,
                    0.0
                ],
                "size": [
                    1.0,
                    1.0,
                    1.0
                ]
            }
        },
        {
            "type": "MESH",
            "name": "Cube.179",
            "transform": {
                "translation": [
                    597.08935546875,
                    148.63153076171875,
                    73.0
                ],
                "rotation": [
                    0.0,
                    -0.0,
                    0.0
                ],
                "scaling": [
                    30.0,
                    10.000000953674316,
                    93.0447006225586
                ]
            },
            "file_name": "cube.gltf",
            "collider": {
                "type": "BOX",
                "center": [
                    0.0,
                    0.0,
                    0.0
                ],
                "size": [
                    1.0,
                    1.0,
                    1.0
                ]
            }
        },
        {
            "type": "MESH",
            "name": "Cube.180",
            "transform": {
                "translation": [
                    573.4253540039062,
                    235.61480712890625,
                    59.40877914428711
                ],
                "rotation": [
                    0.0,
                    -0.0,
                    0.0
                ],
                "scaling": [
                    10.000000953674316,
                    10.000000953674316,
                    66.08507537841797
                ]
            },
            "file_name": "cube.gltf",
            "collider": {
                "type": "BOX",
                "center": [
                    0.0,
                    0.0,
                    0.0
                ],
                "size": [
                    1.0,
                    1.0,
                    1.0
                ]
            }
        },
        {
            "type": "MESH",
            "name": "Cube.181",
            "transform": {
                "translation": [
                    577.167724609375,
                    216.87060546875,
                    95.0
                ],
                "rotation": [
                    0.0,
                    -0.0,
                    0.0
                ],
                "scaling": [
                    30.799997329711914,
                    10.000000953674316,
                    100.52471923828125
                ]
            },
            "file_name": "cube.gltf",
            "collider": {
                "type": "BOX",
                "center": [
                    0.0,
                    0.0,
                    0.0
                ],
                "size": [
                    1.0,
                    1.0,
                    1.0
                ]
            }
        },
        {
            "type": "MESH",
            "name": "Cube.183",
            "transform": {
                "translation": [
                    592.080078125,
                    247.133056640625,
                    73.5116958618164
                ],
                "rotation": [
                    0.0,
                    -0.0,
                    0.0
                ],
                "scaling": [
                    10.000000953674316,
                    10.000000953674316,
                    93.0447006225586
                ]
            },
            "file_name": "cube.gltf",
            "collider": {
                "type": "BOX",
                "center": [
                    0.0,
                    0.0,
                    0.0
                ],
                "size": [
                    1.0,
                    1.0,
                    1.0
                ]
            }
        },
        {
            "type": "MESH",
            "name": "Cube.186",
            "transform": {
                "translation": [
                    599.007568359375,
                    267.21270751953125,
                    62.0345573425293
                ],
                "rotation": [
                    0.0,
                    -0.0,
                    0.0
                ],
                "scaling": [
                    10.000000953674316,
                    10.000000953674316,
                    84.79031372070312
                ]
            },
            "file_name": "cube.gltf",
            "collider": {
                "type": "BOX",
                "center": [
                    0.0,
                    0.0,
                    0.0
                ],
                "size": [
                    1.0,
                    1.0,
                    1.0
                ]
            }
        },
        {
            "type": "MESH",
            "name": "Cube.188",
            "transform": {
                "translation": [
                    578.2671508789062,
                    472.0039367675781,
                    59.40877914428711
                ],
                "rotation": [
                    0.0,
                    -0.0,
                    0.0
                ],
                "scaling": [
                    10.000000953674316,
                    10.000000953674316,
                    66.08507537841797
                ]
            },
            "file_name": "cube.gltf",
            "collider": {
                "type": "BOX",
                "center": [
                    0.0,
                    0.0,
                    0.0
                ],
                "size": [
                    1.0,
                    1.0,
                    1.0
                ]
            }
        },
        {
            "type": "MESH",
            "name": "Cube.195",
            "transform": {
                "translation": [
                    581.9552001953125,
                    420.7464294433594,
                    33.63540267944336
                ],
                "rotation": [
                    0.0,
                    -0.0,
                    0.0
                ],
                "scaling": [
                    10.000000953674316,
                    10.000000953674316,
                    42.53472137451172
                ]
            },
            "file_name": "cube.gltf",
            "collider": {
                "type": "BOX",
                "center": [
                    0.0,
                    0.0,
                    0.0
                ],
                "size": [
                    1.0,
                    1.0,
                    1.0
                ]
            }
        },
        {
            "type": "MESH",
            "name": "Cube.198",
            "transform": {
                "translation": [
                    599.2685546875,
                    553.2646484375,
                    73.5116958618164
                ],
                "rotation": [
                    0.0,
                    -0.0,
                    0.0
                ],
                "scaling": [
                    10.000000953674316,
                    10.000000953674316,
                    93.0447006225586
                ]
            },
            "file_name": "cube.gltf",
            "collider": {
                "type": "BOX",
                "center": [
                    0.0,
                    0.0,
                    0.0
                ],
                "size": [
                    1.0,
                    1.0,
                    1.0
                ]
            }
        },
        {
            "type": "MESH",
            "name": "pillar.North",
            "transform": {
                "translation": [
                    8.004016876220703,
                    675.6949462890625,
                    140.0
                ],
                "rotation": [
                    0.0,
                    -0.0,
                    0.0
                ],
                "scaling": [
                    50.000003814697266,
                    50.000003814697266,
                    150.0
                ]
            },
            "file_name": "cube.gltf",
            "collider": {
                "type": "BOX",
                "center": [
                    0.0,
                    0.0,
                    0.0
                ],
                "size": [
                    1.0,
                    1.0,
                    1.0
                ]
            }
        },
        {
            "type": "MESH",
            "name": "Cube.023",
            "transform": {
                "translation": [
                    -289.8262939453125,
                    -513.9575805664062,
                    73.5116958618164
                ],
                "rotation": [
                    0.0,
                    -0.0,
                    0.0
                ],
                "scaling": [
                    250.00001525878906,
                    30.000001907348633,
                    93.0447006225586
                ]
            },
            "file_name": "cube.gltf",
            "collider": {
                "type": "BOX",
                "center": [
                    0.0,
                    0.0,
                    0.0
                ],
                "size": [
                    1.0,
                    1.0,
                    1.0
                ]
            }
        },
        {
            "type": "MESH",
            "name": "Cube.002",
            "transform": {
                "translation": [
                    -289.3659362792969,
                    691.5309448242188,
                    73.5116958618164
                ],
                "rotation": [
                    0.0,
                    -0.0,
                    0.0
                ],
                "scaling": [
                    250.0,
                    30.0,
                    93.0447006225586
                ]
            },
            "file_name": "cube.gltf",
            "collider": {
                "type": "BOX",
                "center": [
                    0.0,
                    0.0,
                    0.0
                ],
                "size": [
                    1.0,
                    1.0,
                    1.0
                ]
            }
        },
        {
            "type": "MESH",
            "name": "Cube.003",
            "transform": {
                "translation": [
                    303.3169860839844,
                    691.5309448242188,
                    73.5116958618164
                ],
                "rotation": [
                    0.0,
                    -0.0,
                    0.0
                ],
                "scaling": [
                    250.0,
                    30.0,
                    93.0447006225586
                ]
            },
            "file_name": "cube.gltf",
            "collider": {
                "type": "BOX",
                "center": [
                    0.0,
                    0.0,
                    0.0
                ],
                "size": [
                    1.0,
                    1.0,
                    1.0
                ]
            }
        }
    ]
}